ai_prompter/__init__.py
ai_prompter/py.typed
ai_prompter-0.3.1.dist-info/METADATA
ai_prompter-0.3.1.dist-info/WHEEL
ai_prompter-0.3.1.dist-info/licenses/LICENSE
ai_prompter-0.3.1.dist-info/RECORD
