Metadata-Version: 2.4
Name: ai-prompter
Version: 0.3.1
Summary: A prompt management library using Jinja2 templates to build complex prompts easily.
Author-email: LUIS NOVO <lfnovo@gmail.com>
License: MIT
License-File: LICENSE
Requires-Python: >=3.10
Requires-Dist: jinja2>=3.1.6
Requires-Dist: pip>=25.0.1
Requires-Dist: pydantic>=2.0
Provides-Extra: langchain
Requires-Dist: langchain-core>=0.3; extra == 'langchain'
